{"response_code":0,"results":[{"category":"Entertainment: Video Games","type":"multiple","difficulty":"medium","question":"When was the Sega Genesis released in Japan?","correct_answer":"October 29, 1988","incorrect_answers":["August 14, 1989","November 30, 1990","September 1, 1986"]},{"category":"Entertainment: Video Games","type":"multiple","difficulty":"medium","question":"What is the original name of Final Fantasy XV?","correct_answer":"Final Fantasy Versus XIII","incorrect_answers":["Final Fantasy: Reborn","Final Fantasy XVI","Final Fantasy XIII-3"]},{"category":"Entertainment: Video Games","type":"multiple","difficulty":"medium","question":"In Portal 2, the iconic character GLaDOS is turned into:","correct_answer":"A potato","incorrect_answers":["A tomato","A lemon","An apple"]},{"category":"Entertainment: Video Games","type":"multiple","difficulty":"hard","question":"Why was the character Trevor Philips discharged from the Air Force?","correct_answer":"Mental Health Issues","incorrect_answers":["Injuries","Disease","Danger to Others"]},{"category":"Entertainment: Video Games","type":"multiple","difficulty":"easy","question":"What ingredient is NOT used to craft a cake in Minecraft?","correct_answer":"Bread","incorrect_answers":["Wheat","Milk","Egg"]},{"category":"Entertainment: Video Games","type":"multiple","difficulty":"easy","question":"Which of these is NOT a playable character in the 2016 video game Overwatch?","correct_answer":"Invoker","incorrect_answers":["Mercy","Winston","Zenyatta"]},{"category":"Entertainment: Video Games","type":"multiple","difficulty":"easy","question":"The Touhou Project series of games is often associated with which genre?","correct_answer":"Shoot &#039;em up","incorrect_answers":["Strategy","FPS","Casual"]},{"category":"Entertainment: Video Games","type":"multiple","difficulty":"medium","question":"In Fallout 4, which type of power armor is first encountered in the early mission &quot;When Freedom Calls&quot; in a crashed Vertibird?","correct_answer":"T-45","incorrect_answers":["T-51","T-60","X-01"]},{"category":"Entertainment: Video Games","type":"boolean","difficulty":"easy","question":"Rebecca Chambers does not appear in any Resident Evil except for the original Resident Evil and the Gamecube remake.","correct_answer":"False","incorrect_answers":["True"]},{"category":"Entertainment: Video Games","type":"multiple","difficulty":"hard","question":"In the National Pokedex what number is Porygon-Z?","correct_answer":"474","incorrect_answers":["376","432","589"]},{"category":"Entertainment: Video Games","type":"multiple","difficulty":"hard","question":"In the Pok&eacute;mon series, what is Palkia&#039;s hidden ability?","correct_answer":"Telepathy","incorrect_answers":["Pressure","Water Bubble","Hydration"]},{"category":"Entertainment: Video Games","type":"multiple","difficulty":"medium","question":"In Dota 2, what is Earthshaker&#039;s real name?","correct_answer":"Raigor Stonehoof","incorrect_answers":["Banehallow Ambry","Carl","Barathrum"]},{"category":"Entertainment: Video Games","type":"multiple","difficulty":"medium","question":"Which game is NOT part of the Science Adventure series by 5pb. and Nitroplus?","correct_answer":"Occultic; Nine","incorrect_answers":["Steins; Gate","Robotics; Notes","Chaos; Child"]},{"category":"Entertainment: Video Games","type":"multiple","difficulty":"hard","question":"In the &quot;Little Lost Girl&quot; Easter Egg in Call of Duty: Black Ops II, what&#039;s the last step required for the achievement?","correct_answer":"Raise Hell","incorrect_answers":["Freedom","Skewer the Winged Beast","Ascend from Darkness"]},{"category":"Entertainment: Video Games","type":"boolean","difficulty":"medium","question":"In &quot;Starbound&quot;, the track played by the Decorated Music Box is named &quot;Atlas&quot;.","correct_answer":"True","incorrect_answers":["False"]},{"category":"Entertainment: Video Games","type":"multiple","difficulty":"medium","question":"Sean Bean voices the character of &quot;Martin Septim&quot; in which Elder Scrolls game?","correct_answer":"The Elder Scrolls IV: Oblivion","incorrect_answers":["The Elder Scrolls V: Skyrim","The Elder Scrolls III: Morrowind ","The Elder Scrolls Online"]},{"category":"Entertainment: Video Games","type":"multiple","difficulty":"medium","question":"In the &quot;Ace Attorney&quot; series, what is the relationship between Apollo Justice and Trucy Wright?","correct_answer":"They&#039;re half-siblings","incorrect_answers":["They&#039;re co-workers","They&#039;re friends","They&#039;re both attorneys"]},{"category":"Entertainment: Video Games","type":"multiple","difficulty":"easy","question":"In which mall does &quot;Dead Rising&quot; take place?","correct_answer":"Willamette Parkview Mall","incorrect_answers":["Liberty Mall","Twin Pines Mall","Central Square Shopping Center"]},{"category":"Entertainment: Video Games","type":"multiple","difficulty":"medium","question":"In Guild Wars 2, Brooloonu is a small village for which race?","correct_answer":"Quaggan","incorrect_answers":["Kodan","Charr","Tengu"]},{"category":"Entertainment: Video Games","type":"multiple","difficulty":"hard","question":"In Guild Wars 2, what is the name of the Hylek&#039;s sun god?","correct_answer":"Zintl","incorrect_answers":["Huelec","Ameyalli","Cueyatl"]}]}